odoo/addons/pos_config_phone/README.rst
odoo/addons/pos_config_phone/__init__.py
odoo/addons/pos_config_phone/__manifest__.py
odoo/addons/pos_config_phone/i18n/ca.po
odoo/addons/pos_config_phone/i18n/es.po
odoo/addons/pos_config_phone/i18n/it.po
odoo/addons/pos_config_phone/i18n/pos_config_phone.pot
odoo/addons/pos_config_phone/models/__init__.py
odoo/addons/pos_config_phone/models/pos_config.py
odoo/addons/pos_config_phone/models/res_config_settings.py
odoo/addons/pos_config_phone/readme/CONFIGURE.md
odoo/addons/pos_config_phone/readme/CONTRIBUTORS.md
odoo/addons/pos_config_phone/readme/DESCRIPTION.md
odoo/addons/pos_config_phone/readme/USAGE.md
odoo/addons/pos_config_phone/static/description/icon.png
odoo/addons/pos_config_phone/static/description/icon.svg
odoo/addons/pos_config_phone/static/description/index.html
odoo/addons/pos_config_phone/static/src/app/screens/receipt_screen/receipt/receipt_header/receipt_header.xml
odoo/addons/pos_config_phone/static/src/app/store/pos_store.esm.js
odoo/addons/pos_config_phone/views/res_config_settings_views.xml
odoo_addon_pos_config_phone-17.0.1.0.0.4.dist-info/METADATA
odoo_addon_pos_config_phone-17.0.1.0.0.4.dist-info/WHEEL
odoo_addon_pos_config_phone-17.0.1.0.0.4.dist-info/top_level.txt
odoo_addon_pos_config_phone-17.0.1.0.0.4.dist-info/RECORD
